tests/__init__.py
tests/test_models.py
tests/test_text_filter.py
uectl/__init__.py
uectl/models.py
uectl/text_filter.py
uectl/data/orthographic_variants.yml
uectl-0.2.1.dist-info/LICENSE
uectl-0.2.1.dist-info/METADATA
uectl-0.2.1.dist-info/WHEEL
uectl-0.2.1.dist-info/top_level.txt
uectl-0.2.1.dist-info/RECORD
