Metadata-Version: 2.1
Name: uectl
Version: 0.2.1
Summary: @uec_tlに使用するマルコフ連鎖による文章生成とテキスト処理のためのパッケージ
Home-page: https://github.com/A03ki/uec_tl_markov
Author: Aki(@puman03)
Author-email: a03ki04@gmail.com
License: MIT License
Keywords: uectl uec markov
Platform: UNKNOWN
Classifier: License :: OSI Approved :: MIT License
Classifier: Programming Language :: Python :: 3.6
Classifier: Programming Language :: Python :: 3.7
Classifier: Programming Language :: Python :: 3.8
Classifier: Natural Language :: Japanese
Requires-Python: >=3.6, <3.9
Requires-Dist: emoji
Requires-Dist: markovify
Requires-Dist: neologdn
Requires-Dist: pyyaml
Provides-Extra: bot
Requires-Dist: tweepy ; extra == 'bot'
Provides-Extra: preprocessing
Requires-Dist: mecab-python3 (==0.996.5) ; extra == 'preprocessing'
Provides-Extra: tests
Requires-Dist: pytest ; extra == 'tests'
